Workbook

Sheet Übersicht
B1: Budget-Übersicht Simon & Eliana
B2: Alles pro Monat in CHF · rechnet aus dem Blatt «Budget» · Stand 13.10.2026
B4: Gemeinsame Kosten teilen | C4: nach Einkommen | G4: «nach Einkommen»: wer mehr verdient, trägt mehr. «50 / 50»: hälftig.
B6: Bereich | C6: Pro Monat | D6: Pro Jahr | E6: % Einnahmen
B7: Einnahmen | C7: =SUMIFS(Budget!$G$5:$G$300,Budget!$A$5:$A$300,"Einnahmen") | D7: =C7*12 | E7: =IF($C$7=0,0,C7/$C$7) | G7: Rechnet automatisch: jährliche Beträge ÷ 12, vierteljährliche ÷ 3, wöchentliche × 52 ÷ 12.
B8: Wohnen & Energie | C8: =SUMIFS(Budget!$G$5:$G$300,Budget!$A$5:$A$300,B8) | D8: =C8*12 | E8: =IF($C$7=0,0,C8/$C$7)
B9: Versicherungen | C9: =SUMIFS(Budget!$G$5:$G$300,Budget!$A$5:$A$300,B9) | D9: =C9*12 | E9: =IF($C$7=0,0,C9/$C$7)
B10: Steuern | C10: =SUMIFS(Budget!$G$5:$G$300,Budget!$A$5:$A$300,B10) | D10: =C10*12 | E10: =IF($C$7=0,0,C10/$C$7)
B11: Mobilität | C11: =SUMIFS(Budget!$G$5:$G$300,Budget!$A$5:$A$300,B11) | D11: =C11*12 | E11: =IF($C$7=0,0,C11/$C$7)
B12: Haushalt & Essen | C12: =SUMIFS(Budget!$G$5:$G$300,Budget!$A$5:$A$300,B12) | D12: =C12*12 | E12: =IF($C$7=0,0,C12/$C$7)
B13: Persönliches & Freizeit | C13: =SUMIFS(Budget!$G$5:$G$300,Budget!$A$5:$A$300,B13) | D13: =C13*12 | E13: =IF($C$7=0,0,C13/$C$7)
B14: Rückstellungen | C14: =SUMIFS(Budget!$G$5:$G$300,Budget!$A$5:$A$300,B14) | D14: =C14*12 | E14: =IF($C$7=0,0,C14/$C$7)
B15: Ausgaben total | C15: =SUM(C8:C14) | D15: =C15*12 | E15: =IF($C$7=0,0,C15/$C$7)
B16: Sparen & Vorsorge | C16: =SUMIFS(Budget!$G$5:$G$300,Budget!$A$5:$A$300,B16) | D16: =C16*12 | E16: =IF($C$7=0,0,C16/$C$7)
B17: Übrig pro Monat | C17: =C7-C15-C16 | D17: =C17*12 | E17: =IF($C$7=0,0,C17/$C$7) | G17: Positiv = Reserve oder zusätzlich sparen. Negativ (rot) = Budget geht nicht auf.
B21: Wer zahlt was | C21: Simon | D21: Eliana | E21: Zusammen
B22: Einnahmen | C22: =SUMIFS(Budget!$G$5:$G$300,Budget!$A$5:$A$300,"Einnahmen",Budget!$E$5:$E$300,"Simon")+SUMIFS(Budget!$G$5:$G$300,Budget!$A$5:$A$300,"Einnahmen",Budget!$E$5:$E$300,"gemeinsam")/2 | D22: =SUMIFS(Budget!$G$5:$G$300,Budget!$A$5:$A$300,"Einnahmen",Budget!$E$5:$E$300,"Eliana")+SUMIFS(Budget!$G$5:$G$300,Budget!$A$5:$A$300,"Einnahmen",Budget!$E$5:$E$300,"gemeinsam")/2 | E22: =C22+D22
B23: Gemeinsame Kosten (inkl. Rückstellungen und Sparen) | E23: =SUMIFS(Budget!$G$5:$G$300,Budget!$A$5:$A$300,"<>Einnahmen",Budget!$E$5:$E$300,"gemeinsam") | G23: Alle Posten mit «Wer = gemeinsam» ausser Einnahmen.
B24: Anteil an den gemeinsamen Kosten | C24: =IF($C$4="50 / 50",0.5,IF(E22=0,0.5,C22/E22)) | D24: =1-C24 | E24: =C24+D24 | G24: Gemeinsame Einnahmen (z. B. Bonus) zählen je zur Hälfte.
B25: Anteil gemeinsame Kosten in CHF | C25: =$E$23*C24 | D25: =$E$23*D24 | E25: =C25+D25
B26: Eigene Kosten | C26: =SUMIFS(Budget!$G$5:$G$300,Budget!$A$5:$A$300,"<>Einnahmen",Budget!$E$5:$E$300,"Simon") | D26: =SUMIFS(Budget!$G$5:$G$300,Budget!$A$5:$A$300,"<>Einnahmen",Budget!$E$5:$E$300,"Eliana") | E26: =C26+D26
B27: Frei verfügbar | C27: =C22-C25-C26 | D27: =D22-D25-D26 | E27: =C27+D27
B28: Aufs gemeinsame Konto, pro Monat (auf 5 Rp.) | C28: =MROUND(C25,0.05) | D28: =MROUND(D25,0.05) | E28: =C28+D28
B31: Faustregeln (grobe Richtwerte) | C31: Wert | D31: Ziel | E31: Status
B32: Miete im Verhältnis zu den Einnahmen | C32: =IF($C$7=0,0,SUMIFS(Budget!$G$5:$G$300,Budget!$B$5:$B$300,"*Miete*")/$C$7) | D32: =1/3 | E32: =IF(C32<=D32,"✓ erfüllt","✗ zu hoch") | G32: Faustregel: Miete höchstens ein Drittel des Nettoeinkommens.
B33: Sparquote | C33: =IF($C$7=0,0,C16/$C$7) | D33: 0.1 | E33: =IF(C33>=D33,"✓ erfüllt","✗ zu tief") | G33: Faustregel: mindestens 10 % der Einnahmen sparen.
B34: Budget geht auf (übrig ≥ 0) | C34: =C17 | D34: 0 | E34: =IF(C34>=D34,"✓ erfüllt","✗ Defizit")
B35: Für Jahresrechnungen monatlich zurücklegen | C35: =SUMPRODUCT((Budget!$A$5:$A$300<>"Einnahmen")*(Budget!$A$5:$A$300<>"")*((Budget!$D$5:$D$300="jährlich")+(Budget!$D$5:$D$300="halbjährlich")+(Budget!$D$5:$D$300="vierteljährlich"))*Budget!$G$5:$G$300) | G35: Am besten per Dauerauftrag auf ein eigenes Konto.
B36: Notgroschen (drei Monatsausgaben) | C36: =C15*3 | G36: Faustregel: drei Monatsausgaben als Reserve auf dem Sparkonto.
B38: Diese Richtwerte sind übliche Faustregeln, keine Vorgaben einer Beratungsstelle. Für eine persönliche Beratung: Budgetberatung Schweiz (budgetberatung.ch).

Sheet Budget
A1: Haushaltsbudget Simon & Eliana
A2: Blau auf Gelb = eingeben · schwarz = rechnet selbst · Stand 13.10.2026
A3: Zeilen einfügen innerhalb einer Gruppe ist erlaubt – Spalte A muss den Gruppennamen enthalten.
A4: Gruppe | B4: Posten | C4: Betrag CHF | D4: Wie oft | E4: Wer | F4: Fällig Monat | G4: Pro Monat | H4: Pro Jahr | I4: Anteil Simon | J4: Anteil Eliana | K4: Ist-Kategorie
A5: Einnahmen | B5: Nettolohn nach Abzügen, 13. Monatslohn, Nebenverdienst, Zulagen
A6: Einnahmen | B6: Nettolohn Simon | D6: monatlich | E6: Simon | G6: =IFERROR(C6*INDEX(Listen!$B$2:$B$6,MATCH(D6,Listen!$A$2:$A$6,0)),0) | H6: =G6*12 | I6: =IF(E6="Simon",G6,IF(E6="Eliana",0,G6/2)) | J6: =G6-I6
A7: Einnahmen | B7: Nettolohn Eliana | D7: monatlich | E7: Eliana | G7: =IFERROR(C7*INDEX(Listen!$B$2:$B$6,MATCH(D7,Listen!$A$2:$A$6,0)),0) | H7: =G7*12 | I7: =IF(E7="Simon",G7,IF(E7="Eliana",0,G7/2)) | J7: =G7-I7
A8: Einnahmen | B8: 13. Monatslohn Simon | D8: jährlich | E8: Simon | F8: 12 | G8: =IFERROR(C8*INDEX(Listen!$B$2:$B$6,MATCH(D8,Listen!$A$2:$A$6,0)),0) | H8: =G8*12 | I8: =IF(E8="Simon",G8,IF(E8="Eliana",0,G8/2)) | J8: =G8-I8
A9: Einnahmen | B9: 13. Monatslohn Eliana | D9: jährlich | E9: Eliana | F9: 12 | G9: =IFERROR(C9*INDEX(Listen!$B$2:$B$6,MATCH(D9,Listen!$A$2:$A$6,0)),0) | H9: =G9*12 | I9: =IF(E9="Simon",G9,IF(E9="Eliana",0,G9/2)) | J9: =G9-I9
A10: Einnahmen | B10: Nebenverdienst, Bonus | D10: jährlich | E10: gemeinsam | F10: 1 | G10: =IFERROR(C10*INDEX(Listen!$B$2:$B$6,MATCH(D10,Listen!$A$2:$A$6,0)),0) | H10: =G10*12 | I10: =IF(E10="Simon",G10,IF(E10="Eliana",0,G10/2)) | J10: =G10-I10
A11: Einnahmen | D11: monatlich | E11: gemeinsam | G11: =IFERROR(C11*INDEX(Listen!$B$2:$B$6,MATCH(D11,Listen!$A$2:$A$6,0)),0) | H11: =G11*12 | I11: =IF(E11="Simon",G11,IF(E11="Eliana",0,G11/2)) | J11: =G11-I11
A12: Einnahmen | D12: monatlich | E12: gemeinsam | G12: =IFERROR(C12*INDEX(Listen!$B$2:$B$6,MATCH(D12,Listen!$A$2:$A$6,0)),0) | H12: =G12*12 | I12: =IF(E12="Simon",G12,IF(E12="Eliana",0,G12/2)) | J12: =G12-I12
A13: Einnahmen | D13: monatlich | E13: gemeinsam | G13: =IFERROR(C13*INDEX(Listen!$B$2:$B$6,MATCH(D13,Listen!$A$2:$A$6,0)),0) | H13: =G13*12 | I13: =IF(E13="Simon",G13,IF(E13="Eliana",0,G13/2)) | J13: =G13-I13
A14: Wohnen & Energie | B14: Miete mit Nebenkosten, Strom, Internet, Serafe
A15: Wohnen & Energie | B15: Miete inkl. Nebenkosten | D15: monatlich | E15: gemeinsam | G15: =IFERROR(C15*INDEX(Listen!$B$2:$B$6,MATCH(D15,Listen!$A$2:$A$6,0)),0) | H15: =G15*12 | I15: =IF(E15="Simon",G15,IF(E15="Eliana",0,G15*'Übersicht'!$C$24)) | J15: =G15-I15
A16: Wohnen & Energie | B16: Strom | D16: vierteljährlich | E16: gemeinsam | F16: 3 | G16: =IFERROR(C16*INDEX(Listen!$B$2:$B$6,MATCH(D16,Listen!$A$2:$A$6,0)),0) | H16: =G16*12 | I16: =IF(E16="Simon",G16,IF(E16="Eliana",0,G16*'Übersicht'!$C$24)) | J16: =G16-I16
A17: Wohnen & Energie | B17: Internet & TV | D17: monatlich | E17: gemeinsam | G17: =IFERROR(C17*INDEX(Listen!$B$2:$B$6,MATCH(D17,Listen!$A$2:$A$6,0)),0) | H17: =G17*12 | I17: =IF(E17="Simon",G17,IF(E17="Eliana",0,G17*'Übersicht'!$C$24)) | J17: =G17-I17
A18: Wohnen & Energie | B18: Serafe (Radio/TV-Abgabe) | D18: jährlich | E18: gemeinsam | F18: 4 | G18: =IFERROR(C18*INDEX(Listen!$B$2:$B$6,MATCH(D18,Listen!$A$2:$A$6,0)),0) | H18: =G18*12 | I18: =IF(E18="Simon",G18,IF(E18="Eliana",0,G18*'Übersicht'!$C$24)) | J18: =G18-I18
A19: Wohnen & Energie | D19: monatlich | E19: gemeinsam | G19: =IFERROR(C19*INDEX(Listen!$B$2:$B$6,MATCH(D19,Listen!$A$2:$A$6,0)),0) | H19: =G19*12 | I19: =IF(E19="Simon",G19,IF(E19="Eliana",0,G19*'Übersicht'!$C$24)) | J19: =G19-I19
A20: Wohnen & Energie | D20: monatlich | E20: gemeinsam | G20: =IFERROR(C20*INDEX(Listen!$B$2:$B$6,MATCH(D20,Listen!$A$2:$A$6,0)),0) | H20: =G20*12 | I20: =IF(E20="Simon",G20,IF(E20="Eliana",0,G20*'Übersicht'!$C$24)) | J20: =G20-I20
A21: Wohnen & Energie | D21: monatlich | E21: gemeinsam | G21: =IFERROR(C21*INDEX(Listen!$B$2:$B$6,MATCH(D21,Listen!$A$2:$A$6,0)),0) | H21: =G21*12 | I21: =IF(E21="Simon",G21,IF(E21="Eliana",0,G21*'Übersicht'!$C$24)) | J21: =G21-I21
A22: Versicherungen | B22: Krankenkasse, Zusatzversicherungen, Hausrat und Haftpflicht
A23: Versicherungen | B23: Krankenkasse Simon | D23: monatlich | E23: Simon | G23: =IFERROR(C23*INDEX(Listen!$B$2:$B$6,MATCH(D23,Listen!$A$2:$A$6,0)),0) | H23: =G23*12 | I23: =IF(E23="Simon",G23,IF(E23="Eliana",0,G23*'Übersicht'!$C$24)) | J23: =G23-I23
A24: Versicherungen | B24: Krankenkasse Eliana | D24: monatlich | E24: Eliana | G24: =IFERROR(C24*INDEX(Listen!$B$2:$B$6,MATCH(D24,Listen!$A$2:$A$6,0)),0) | H24: =G24*12 | I24: =IF(E24="Simon",G24,IF(E24="Eliana",0,G24*'Übersicht'!$C$24)) | J24: =G24-I24
A25: Versicherungen | B25: Zusatzversicherungen | D25: monatlich | E25: gemeinsam | G25: =IFERROR(C25*INDEX(Listen!$B$2:$B$6,MATCH(D25,Listen!$A$2:$A$6,0)),0) | H25: =G25*12 | I25: =IF(E25="Simon",G25,IF(E25="Eliana",0,G25*'Übersicht'!$C$24)) | J25: =G25-I25
A26: Versicherungen | B26: Hausrat & Privathaftpflicht | D26: jährlich | E26: gemeinsam | F26: 1 | G26: =IFERROR(C26*INDEX(Listen!$B$2:$B$6,MATCH(D26,Listen!$A$2:$A$6,0)),0) | H26: =G26*12 | I26: =IF(E26="Simon",G26,IF(E26="Eliana",0,G26*'Übersicht'!$C$24)) | J26: =G26-I26
A27: Versicherungen | D27: monatlich | E27: gemeinsam | G27: =IFERROR(C27*INDEX(Listen!$B$2:$B$6,MATCH(D27,Listen!$A$2:$A$6,0)),0) | H27: =G27*12 | I27: =IF(E27="Simon",G27,IF(E27="Eliana",0,G27*'Übersicht'!$C$24)) | J27: =G27-I27
A28: Versicherungen | D28: monatlich | E28: gemeinsam | G28: =IFERROR(C28*INDEX(Listen!$B$2:$B$6,MATCH(D28,Listen!$A$2:$A$6,0)),0) | H28: =G28*12 | I28: =IF(E28="Simon",G28,IF(E28="Eliana",0,G28*'Übersicht'!$C$24)) | J28: =G28-I28
A29: Versicherungen | D29: monatlich | E29: gemeinsam | G29: =IFERROR(C29*INDEX(Listen!$B$2:$B$6,MATCH(D29,Listen!$A$2:$A$6,0)),0) | H29: =G29*12 | I29: =IF(E29="Simon",G29,IF(E29="Eliana",0,G29*'Übersicht'!$C$24)) | J29: =G29-I29
A30: Steuern | B30: Gemeinde-, Staats- und Bundessteuer – als Jahresbetrag
A31: Steuern | B31: Steuern Simon | D31: jährlich | E31: Simon | F31: 3 | G31: =IFERROR(C31*INDEX(Listen!$B$2:$B$6,MATCH(D31,Listen!$A$2:$A$6,0)),0) | H31: =G31*12 | I31: =IF(E31="Simon",G31,IF(E31="Eliana",0,G31*'Übersicht'!$C$24)) | J31: =G31-I31
A32: Steuern | B32: Steuern Eliana | D32: jährlich | E32: Eliana | F32: 3 | G32: =IFERROR(C32*INDEX(Listen!$B$2:$B$6,MATCH(D32,Listen!$A$2:$A$6,0)),0) | H32: =G32*12 | I32: =IF(E32="Simon",G32,IF(E32="Eliana",0,G32*'Übersicht'!$C$24)) | J32: =G32-I32
A33: Steuern | D33: monatlich | E33: gemeinsam | G33: =IFERROR(C33*INDEX(Listen!$B$2:$B$6,MATCH(D33,Listen!$A$2:$A$6,0)),0) | H33: =G33*12 | I33: =IF(E33="Simon",G33,IF(E33="Eliana",0,G33*'Übersicht'!$C$24)) | J33: =G33-I33
A34: Steuern | D34: monatlich | E34: gemeinsam | G34: =IFERROR(C34*INDEX(Listen!$B$2:$B$6,MATCH(D34,Listen!$A$2:$A$6,0)),0) | H34: =G34*12 | I34: =IF(E34="Simon",G34,IF(E34="Eliana",0,G34*'Übersicht'!$C$24)) | J34: =G34-I34
A35: Steuern | D35: monatlich | E35: gemeinsam | G35: =IFERROR(C35*INDEX(Listen!$B$2:$B$6,MATCH(D35,Listen!$A$2:$A$6,0)),0) | H35: =G35*12 | I35: =IF(E35="Simon",G35,IF(E35="Eliana",0,G35*'Übersicht'!$C$24)) | J35: =G35-I35
A36: Mobilität | B36: ÖV-Abo, Halbtax, Velo, Auto
A37: Mobilität | B37: ÖV-Abo Simon | D37: jährlich | E37: Simon | F37: 1 | G37: =IFERROR(C37*INDEX(Listen!$B$2:$B$6,MATCH(D37,Listen!$A$2:$A$6,0)),0) | H37: =G37*12 | I37: =IF(E37="Simon",G37,IF(E37="Eliana",0,G37*'Übersicht'!$C$24)) | J37: =G37-I37
A38: Mobilität | B38: ÖV-Abo Eliana | D38: jährlich | E38: Eliana | F38: 1 | G38: =IFERROR(C38*INDEX(Listen!$B$2:$B$6,MATCH(D38,Listen!$A$2:$A$6,0)),0) | H38: =G38*12 | I38: =IF(E38="Simon",G38,IF(E38="Eliana",0,G38*'Übersicht'!$C$24)) | J38: =G38-I38
A39: Mobilität | B39: Velo, Unterhalt | D39: jährlich | E39: gemeinsam | F39: 4 | G39: =IFERROR(C39*INDEX(Listen!$B$2:$B$6,MATCH(D39,Listen!$A$2:$A$6,0)),0) | H39: =G39*12 | I39: =IF(E39="Simon",G39,IF(E39="Eliana",0,G39*'Übersicht'!$C$24)) | J39: =G39-I39
A40: Mobilität | D40: monatlich | E40: gemeinsam | G40: =IFERROR(C40*INDEX(Listen!$B$2:$B$6,MATCH(D40,Listen!$A$2:$A$6,0)),0) | H40: =G40*12 | I40: =IF(E40="Simon",G40,IF(E40="Eliana",0,G40*'Übersicht'!$C$24)) | J40: =G40-I40
A41: Mobilität | D41: monatlich | E41: gemeinsam | G41: =IFERROR(C41*INDEX(Listen!$B$2:$B$6,MATCH(D41,Listen!$A$2:$A$6,0)),0) | H41: =G41*12 | I41: =IF(E41="Simon",G41,IF(E41="Eliana",0,G41*'Übersicht'!$C$24)) | J41: =G41-I41
A42: Mobilität | D42: monatlich | E42: gemeinsam | G42: =IFERROR(C42*INDEX(Listen!$B$2:$B$6,MATCH(D42,Listen!$A$2:$A$6,0)),0) | H42: =G42*12 | I42: =IF(E42="Simon",G42,IF(E42="Eliana",0,G42*'Übersicht'!$C$24)) | J42: =G42-I42
A43: Haushalt & Essen | B43: Lebensmittel, Auswärts essen, Drogerie
A44: Haushalt & Essen | B44: Lebensmittel & Getränke | D44: monatlich | E44: gemeinsam | G44: =IFERROR(C44*INDEX(Listen!$B$2:$B$6,MATCH(D44,Listen!$A$2:$A$6,0)),0) | H44: =G44*12 | I44: =IF(E44="Simon",G44,IF(E44="Eliana",0,G44*'Übersicht'!$C$24)) | J44: =G44-I44 | K44: Lebensmittel
A45: Haushalt & Essen | B45: Auswärts essen | D45: monatlich | E45: gemeinsam | G45: =IFERROR(C45*INDEX(Listen!$B$2:$B$6,MATCH(D45,Listen!$A$2:$A$6,0)),0) | H45: =G45*12 | I45: =IF(E45="Simon",G45,IF(E45="Eliana",0,G45*'Übersicht'!$C$24)) | J45: =G45-I45 | K45: Auswärts
A46: Haushalt & Essen | B46: Drogerie & Haushaltartikel | D46: monatlich | E46: gemeinsam | G46: =IFERROR(C46*INDEX(Listen!$B$2:$B$6,MATCH(D46,Listen!$A$2:$A$6,0)),0) | H46: =G46*12 | I46: =IF(E46="Simon",G46,IF(E46="Eliana",0,G46*'Übersicht'!$C$24)) | J46: =G46-I46
A47: Haushalt & Essen | D47: monatlich | E47: gemeinsam | G47: =IFERROR(C47*INDEX(Listen!$B$2:$B$6,MATCH(D47,Listen!$A$2:$A$6,0)),0) | H47: =G47*12 | I47: =IF(E47="Simon",G47,IF(E47="Eliana",0,G47*'Übersicht'!$C$24)) | J47: =G47-I47
A48: Haushalt & Essen | D48: monatlich | E48: gemeinsam | G48: =IFERROR(C48*INDEX(Listen!$B$2:$B$6,MATCH(D48,Listen!$A$2:$A$6,0)),0) | H48: =G48*12 | I48: =IF(E48="Simon",G48,IF(E48="Eliana",0,G48*'Übersicht'!$C$24)) | J48: =G48-I48
A49: Haushalt & Essen | D49: monatlich | E49: gemeinsam | G49: =IFERROR(C49*INDEX(Listen!$B$2:$B$6,MATCH(D49,Listen!$A$2:$A$6,0)),0) | H49: =G49*12 | I49: =IF(E49="Simon",G49,IF(E49="Eliana",0,G49*'Übersicht'!$C$24)) | J49: =G49-I49
A50: Persönliches & Freizeit | B50: Handy, Kleider, Coiffeur, Sport, Abos, Geschenke
A51: Persönliches & Freizeit | B51: Handy-Abo Simon | D51: monatlich | E51: Simon | G51: =IFERROR(C51*INDEX(Listen!$B$2:$B$6,MATCH(D51,Listen!$A$2:$A$6,0)),0) | H51: =G51*12 | I51: =IF(E51="Simon",G51,IF(E51="Eliana",0,G51*'Übersicht'!$C$24)) | J51: =G51-I51
A52: Persönliches & Freizeit | B52: Handy-Abo Eliana | D52: monatlich | E52: Eliana | G52: =IFERROR(C52*INDEX(Listen!$B$2:$B$6,MATCH(D52,Listen!$A$2:$A$6,0)),0) | H52: =G52*12 | I52: =IF(E52="Simon",G52,IF(E52="Eliana",0,G52*'Übersicht'!$C$24)) | J52: =G52-I52
A53: Persönliches & Freizeit | B53: Kleider & Schuhe | D53: monatlich | E53: gemeinsam | G53: =IFERROR(C53*INDEX(Listen!$B$2:$B$6,MATCH(D53,Listen!$A$2:$A$6,0)),0) | H53: =G53*12 | I53: =IF(E53="Simon",G53,IF(E53="Eliana",0,G53*'Übersicht'!$C$24)) | J53: =G53-I53
A54: Persönliches & Freizeit | B54: Coiffeur & Körperpflege | D54: monatlich | E54: gemeinsam | G54: =IFERROR(C54*INDEX(Listen!$B$2:$B$6,MATCH(D54,Listen!$A$2:$A$6,0)),0) | H54: =G54*12 | I54: =IF(E54="Simon",G54,IF(E54="Eliana",0,G54*'Übersicht'!$C$24)) | J54: =G54-I54
A55: Persönliches & Freizeit | B55: Sport & Fitness | D55: monatlich | E55: gemeinsam | G55: =IFERROR(C55*INDEX(Listen!$B$2:$B$6,MATCH(D55,Listen!$A$2:$A$6,0)),0) | H55: =G55*12 | I55: =IF(E55="Simon",G55,IF(E55="Eliana",0,G55*'Übersicht'!$C$24)) | J55: =G55-I55
A56: Persönliches & Freizeit | B56: Streaming & Abos | D56: monatlich | E56: gemeinsam | G56: =IFERROR(C56*INDEX(Listen!$B$2:$B$6,MATCH(D56,Listen!$A$2:$A$6,0)),0) | H56: =G56*12 | I56: =IF(E56="Simon",G56,IF(E56="Eliana",0,G56*'Übersicht'!$C$24)) | J56: =G56-I56
A57: Persönliches & Freizeit | B57: Hobbys & Ausgang | D57: monatlich | E57: gemeinsam | G57: =IFERROR(C57*INDEX(Listen!$B$2:$B$6,MATCH(D57,Listen!$A$2:$A$6,0)),0) | H57: =G57*12 | I57: =IF(E57="Simon",G57,IF(E57="Eliana",0,G57*'Übersicht'!$C$24)) | J57: =G57-I57
A58: Persönliches & Freizeit | B58: Geschenke | D58: jährlich | E58: gemeinsam | F58: 12 | G58: =IFERROR(C58*INDEX(Listen!$B$2:$B$6,MATCH(D58,Listen!$A$2:$A$6,0)),0) | H58: =G58*12 | I58: =IF(E58="Simon",G58,IF(E58="Eliana",0,G58*'Übersicht'!$C$24)) | J58: =G58-I58
A59: Persönliches & Freizeit | D59: monatlich | E59: gemeinsam | G59: =IFERROR(C59*INDEX(Listen!$B$2:$B$6,MATCH(D59,Listen!$A$2:$A$6,0)),0) | H59: =G59*12 | I59: =IF(E59="Simon",G59,IF(E59="Eliana",0,G59*'Übersicht'!$C$24)) | J59: =G59-I59
A60: Persönliches & Freizeit | D60: monatlich | E60: gemeinsam | G60: =IFERROR(C60*INDEX(Listen!$B$2:$B$6,MATCH(D60,Listen!$A$2:$A$6,0)),0) | H60: =G60*12 | I60: =IF(E60="Simon",G60,IF(E60="Eliana",0,G60*'Übersicht'!$C$24)) | J60: =G60-I60
A61: Rückstellungen | B61: Ferien, Zahnarzt und Franchise, Anschaffungen, Unvorhergesehenes
A62: Rückstellungen | B62: Ferien | D62: jährlich | E62: gemeinsam | F62: 7 | G62: =IFERROR(C62*INDEX(Listen!$B$2:$B$6,MATCH(D62,Listen!$A$2:$A$6,0)),0) | H62: =G62*12 | I62: =IF(E62="Simon",G62,IF(E62="Eliana",0,G62*'Übersicht'!$C$24)) | J62: =G62-I62
A63: Rückstellungen | B63: Gesundheit: Franchise, Zahnarzt, Brille | D63: jährlich | E63: gemeinsam | F63: 1 | G63: =IFERROR(C63*INDEX(Listen!$B$2:$B$6,MATCH(D63,Listen!$A$2:$A$6,0)),0) | H63: =G63*12 | I63: =IF(E63="Simon",G63,IF(E63="Eliana",0,G63*'Übersicht'!$C$24)) | J63: =G63-I63
A64: Rückstellungen | B64: Anschaffungen & Ersatz | D64: jährlich | E64: gemeinsam | F64: 11 | G64: =IFERROR(C64*INDEX(Listen!$B$2:$B$6,MATCH(D64,Listen!$A$2:$A$6,0)),0) | H64: =G64*12 | I64: =IF(E64="Simon",G64,IF(E64="Eliana",0,G64*'Übersicht'!$C$24)) | J64: =G64-I64
A65: Rückstellungen | B65: Unvorhergesehenes | D65: monatlich | E65: gemeinsam | G65: =IFERROR(C65*INDEX(Listen!$B$2:$B$6,MATCH(D65,Listen!$A$2:$A$6,0)),0) | H65: =G65*12 | I65: =IF(E65="Simon",G65,IF(E65="Eliana",0,G65*'Übersicht'!$C$24)) | J65: =G65-I65
A66: Rückstellungen | D66: monatlich | E66: gemeinsam | G66: =IFERROR(C66*INDEX(Listen!$B$2:$B$6,MATCH(D66,Listen!$A$2:$A$6,0)),0) | H66: =G66*12 | I66: =IF(E66="Simon",G66,IF(E66="Eliana",0,G66*'Übersicht'!$C$24)) | J66: =G66-I66
A67: Rückstellungen | D67: monatlich | E67: gemeinsam | G67: =IFERROR(C67*INDEX(Listen!$B$2:$B$6,MATCH(D67,Listen!$A$2:$A$6,0)),0) | H67: =G67*12 | I67: =IF(E67="Simon",G67,IF(E67="Eliana",0,G67*'Übersicht'!$C$24)) | J67: =G67-I67
A68: Rückstellungen | D68: monatlich | E68: gemeinsam | G68: =IFERROR(C68*INDEX(Listen!$B$2:$B$6,MATCH(D68,Listen!$A$2:$A$6,0)),0) | H68: =G68*12 | I68: =IF(E68="Simon",G68,IF(E68="Eliana",0,G68*'Übersicht'!$C$24)) | J68: =G68-I68
A69: Sparen & Vorsorge | B69: Sparkonto, Notgroschen, Säule 3a
A70: Sparen & Vorsorge | B70: Sparkonto, Notgroschen | D70: monatlich | E70: gemeinsam | G70: =IFERROR(C70*INDEX(Listen!$B$2:$B$6,MATCH(D70,Listen!$A$2:$A$6,0)),0) | H70: =G70*12 | I70: =IF(E70="Simon",G70,IF(E70="Eliana",0,G70*'Übersicht'!$C$24)) | J70: =G70-I70
A71: Sparen & Vorsorge | B71: Säule 3a Simon | D71: jährlich | E71: Simon | F71: 12 | G71: =IFERROR(C71*INDEX(Listen!$B$2:$B$6,MATCH(D71,Listen!$A$2:$A$6,0)),0) | H71: =G71*12 | I71: =IF(E71="Simon",G71,IF(E71="Eliana",0,G71*'Übersicht'!$C$24)) | J71: =G71-I71
A72: Sparen & Vorsorge | B72: Säule 3a Eliana | D72: jährlich | E72: Eliana | F72: 12 | G72: =IFERROR(C72*INDEX(Listen!$B$2:$B$6,MATCH(D72,Listen!$A$2:$A$6,0)),0) | H72: =G72*12 | I72: =IF(E72="Simon",G72,IF(E72="Eliana",0,G72*'Übersicht'!$C$24)) | J72: =G72-I72
A73: Sparen & Vorsorge | D73: monatlich | E73: gemeinsam | G73: =IFERROR(C73*INDEX(Listen!$B$2:$B$6,MATCH(D73,Listen!$A$2:$A$6,0)),0) | H73: =G73*12 | I73: =IF(E73="Simon",G73,IF(E73="Eliana",0,G73*'Übersicht'!$C$24)) | J73: =G73-I73
A74: Sparen & Vorsorge | D74: monatlich | E74: gemeinsam | G74: =IFERROR(C74*INDEX(Listen!$B$2:$B$6,MATCH(D74,Listen!$A$2:$A$6,0)),0) | H74: =G74*12 | I74: =IF(E74="Simon",G74,IF(E74="Eliana",0,G74*'Übersicht'!$C$24)) | J74: =G74-I74
A75: Sparen & Vorsorge | D75: monatlich | E75: gemeinsam | G75: =IFERROR(C75*INDEX(Listen!$B$2:$B$6,MATCH(D75,Listen!$A$2:$A$6,0)),0) | H75: =G75*12 | I75: =IF(E75="Simon",G75,IF(E75="Eliana",0,G75*'Übersicht'!$C$24)) | J75: =G75-I75
B77: Kontrolle: Summe aller Posten pro Monat | G77: =SUM(G5:G75) | I77: =SUM(I5:I75) | J77: =SUM(J5:J75)

Sheet Jahresplan
A1: Jahresplan – Geldflüsse pro Monat
A2: Monatliche Posten jeden Monat, jährliche im Fälligkeitsmonat, halbjährliche alle 6, vierteljährliche alle 3 Monate ab dem Fälligkeitsmonat.
B4: Jan | C4: Feb | D4: Mär | E4: Apr | F4: Mai | G4: Jun | H4: Jul | I4: Aug | J4: Sep | K4: Okt | L4: Nov | M4: Dez | N4: Jahr
A5: Monat Nr. | B5: 1 | C5: 2 | D5: 3 | E5: 4 | F5: 5 | G5: 6 | H5: 7 | I5: 8 | J5: 9 | K5: 10 | L5: 11 | M5: 12
A6: Einnahmen | B6: =SUMPRODUCT((Budget!$A$5:$A$300="Einnahmen")*(((Budget!$D$5:$D$300="monatlich")+(Budget!$D$5:$D$300="wöchentlich")*52/12)*Budget!$C$5:$C$300+((Budget!$D$5:$D$300="jährlich")*(Budget!$F$5:$F$300=B$5)+(Budget!$D$5:$D$300="halbjährlich")*(MOD(B$5-Budget!$F$5:$F$300,6)=0)+(Budget!$D$5:$D$300="vierteljährlich")*(MOD(B$5-Budget!$F$5:$F$300,3)=0))*Budget!$C$5:$C$300)) | C6: =SUMPRODUCT((Budget!$A$5:$A$300="Einnahmen")*(((Budget!$D$5:$D$300="monatlich")+(Budget!$D$5:$D$300="wöchentlich")*52/12)*Budget!$C$5:$C$300+((Budget!$D$5:$D$300="jährlich")*(Budget!$F$5:$F$300=C$5)+(Budget!$D$5:$D$300="halbjährlich")*(MOD(C$5-Budget!$F$5:$F$300,6)=0)+(Budget!$D$5:$D$300="vierteljährlich")*(MOD(C$5-Budget!$F$5:$F$300,3)=0))*Budget!$C$5:$C$300)) | D6: =SUMPRODUCT((Budget!$A$5:$A$300="Einnahmen")*(((Budget!$D$5:$D$300="monatlich")+(Budget!$D$5:$D$300="wöchentlich")*52/12)*Budget!$C$5:$C$300+((Budget!$D$5:$D$300="jährlich")*(Budget!$F$5:$F$300=D$5)+(Budget!$D$5:$D$300="halbjährlich")*(MOD(D$5-Budget!$F$5:$F$300,6)=0)+(Budget!$D$5:$D$300="vierteljährlich")*(MOD(D$5-Budget!$F$5:$F$300,3)=0))*Budget!$C$5:$C$300)) | E6: =SUMPRODUCT((Budget!$A$5:$A$300="Einnahmen")*(((Budget!$D$5:$D$300="monatlich")+(Budget!$D$5:$D$300="wöchentlich")*52/12)*Budget!$C$5:$C$300+((Budget!$D$5:$D$300="jährlich")*(Budget!$F$5:$F$300=E$5)+(Budget!$D$5:$D$300="halbjährlich")*(MOD(E$5-Budget!$F$5:$F$300,6)=0)+(Budget!$D$5:$D$300="vierteljährlich")*(MOD(E$5-Budget!$F$5:$F$300,3)=0))*Budget!$C$5:$C$300)) | F6: =SUMPRODUCT((Budget!$A$5:$A$300="Einnahmen")*(((Budget!$D$5:$D$300="monatlich")+(Budget!$D$5:$D$300="wöchentlich")*52/12)*Budget!$C$5:$C$300+((Budget!$D$5:$D$300="jährlich")*(Budget!$F$5:$F$300=F$5)+(Budget!$D$5:$D$300="halbjährlich")*(MOD(F$5-Budget!$F$5:$F$300,6)=0)+(Budget!$D$5:$D$300="vierteljährlich")*(MOD(F$5-Budget!$F$5:$F$300,3)=0))*Budget!$C$5:$C$300)) | G6: =SUMPRODUCT((Budget!$A$5:$A$300="Einnahmen")*(((Budget!$D$5:$D$300="monatlich")+(Budget!$D$5:$D$300="wöchentlich")*52/12)*Budget!$C$5:$C$300+((Budget!$D$5:$D$300="jährlich")*(Budget!$F$5:$F$300=G$5)+(Budget!$D$5:$D$300="halbjährlich")*(MOD(G$5-Budget!$F$5:$F$300,6)=0)+(Budget!$D$5:$D$300="vierteljährlich")*(MOD(G$5-Budget!$F$5:$F$300,3)=0))*Budget!$C$5:$C$300)) | H6: =SUMPRODUCT((Budget!$A$5:$A$300="Einnahmen")*(((Budget!$D$5:$D$300="monatlich")+(Budget!$D$5:$D$300="wöchentlich")*52/12)*Budget!$C$5:$C$300+((Budget!$D$5:$D$300="jährlich")*(Budget!$F$5:$F$300=H$5)+(Budget!$D$5:$D$300="halbjährlich")*(MOD(H$5-Budget!$F$5:$F$300,6)=0)+(Budget!$D$5:$D$300="vierteljährlich")*(MOD(H$5-Budget!$F$5:$F$300,3)=0))*Budget!$C$5:$C$300)) | I6: =SUMPRODUCT((Budget!$A$5:$A$300="Einnahmen")*(((Budget!$D$5:$D$300="monatlich")+(Budget!$D$5:$D$300="wöchentlich")*52/12)*Budget!$C$5:$C$300+((Budget!$D$5:$D$300="jährlich")*(Budget!$F$5:$F$300=I$5)+(Budget!$D$5:$D$300="halbjährlich")*(MOD(I$5-Budget!$F$5:$F$300,6)=0)+(Budget!$D$5:$D$300="vierteljährlich")*(MOD(I$5-Budget!$F$5:$F$300,3)=0))*Budget!$C$5:$C$300)) | ... M6: =SUMPRODUCT((Budget!$A$5:$A$300="Einnahmen")*(((Budget!$D$5:$D$300="monatlich")+(Budget!$D$5:$D$300="wöchentlich")*52/12)*Budget!$C$5:$C$300+((Budget!$D$5:$D$300="jährlich")*(Budget!$F$5:$F$300=M$5)+(Budget!$D$5:$D$300="halbjährlich")*(MOD(M$5-Budget!$F$5:$F$300,6)=0)+(Budget!$D$5:$D$300="vierteljährlich")*(MOD(M$5-Budget!$F$5:$F$300,3)=0))*Budget!$C$5:$C$300)) | N6: =SUM(B6:M6)
A7: Ausgaben (inkl. Rückstellungen und Sparen) | B7: =SUMPRODUCT((Budget!$A$5:$A$300<>"Einnahmen")*(Budget!$A$5:$A$300<>"")*(((Budget!$D$5:$D$300="monatlich")+(Budget!$D$5:$D$300="wöchentlich")*52/12)*Budget!$C$5:$C$300+((Budget!$D$5:$D$300="jährlich")*(Budget!$F$5:$F$300=B$5)+(Budget!$D$5:$D$300="halbjährlich")*(MOD(B$5-Budget!$F$5:$F$300,6)=0)+(Budget!$D$5:$D$300="vierteljährlich")*(MOD(B$5-Budget!$F$5:$F$300,3)=0))*Budget!$C$5:$C$300)) | C7: =SUMPRODUCT((Budget!$A$5:$A$300<>"Einnahmen")*(Budget!$A$5:$A$300<>"")*(((Budget!$D$5:$D$300="monatlich")+(Budget!$D$5:$D$300="wöchentlich")*52/12)*Budget!$C$5:$C$300+((Budget!$D$5:$D$300="jährlich")*(Budget!$F$5:$F$300=C$5)+(Budget!$D$5:$D$300="halbjährlich")*(MOD(C$5-Budget!$F$5:$F$300,6)=0)+(Budget!$D$5:$D$300="vierteljährlich")*(MOD(C$5-Budget!$F$5:$F$300,3)=0))*Budget!$C$5:$C$300)) | D7: =SUMPRODUCT((Budget!$A$5:$A$300<>"Einnahmen")*(Budget!$A$5:$A$300<>"")*(((Budget!$D$5:$D$300="monatlich")+(Budget!$D$5:$D$300="wöchentlich")*52/12)*Budget!$C$5:$C$300+((Budget!$D$5:$D$300="jährlich")*(Budget!$F$5:$F$300=D$5)+(Budget!$D$5:$D$300="halbjährlich")*(MOD(D$5-Budget!$F$5:$F$300,6)=0)+(Budget!$D$5:$D$300="vierteljährlich")*(MOD(D$5-Budget!$F$5:$F$300,3)=0))*Budget!$C$5:$C$300)) | E7: =SUMPRODUCT((Budget!$A$5:$A$300<>"Einnahmen")*(Budget!$A$5:$A$300<>"")*(((Budget!$D$5:$D$300="monatlich")+(Budget!$D$5:$D$300="wöchentlich")*52/12)*Budget!$C$5:$C$300+((Budget!$D$5:$D$300="jährlich")*(Budget!$F$5:$F$300=E$5)+(Budget!$D$5:$D$300="halbjährlich")*(MOD(E$5-Budget!$F$5:$F$300,6)=0)+(Budget!$D$5:$D$300="vierteljährlich")*(MOD(E$5-Budget!$F$5:$F$300,3)=0))*Budget!$C$5:$C$300)) | F7: =SUMPRODUCT((Budget!$A$5:$A$300<>"Einnahmen")*(Budget!$A$5:$A$300<>"")*(((Budget!$D$5:$D$300="monatlich")+(Budget!$D$5:$D$300="wöchentlich")*52/12)*Budget!$C$5:$C$300+((Budget!$D$5:$D$300="jährlich")*(Budget!$F$5:$F$300=F$5)+(Budget!$D$5:$D$300="halbjährlich")*(MOD(F$5-Budget!$F$5:$F$300,6)=0)+(Budget!$D$5:$D$300="vierteljährlich")*(MOD(F$5-Budget!$F$5:$F$300,3)=0))*Budget!$C$5:$C$300)) | G7: =SUMPRODUCT((Budget!$A$5:$A$300<>"Einnahmen")*(Budget!$A$5:$A$300<>"")*(((Budget!$D$5:$D$300="monatlich")+(Budget!$D$5:$D$300="wöchentlich")*52/12)*Budget!$C$5:$C$300+((Budget!$D$5:$D$300="jährlich")*(Budget!$F$5:$F$300=G$5)+(Budget!$D$5:$D$300="halbjährlich")*(MOD(G$5-Budget!$F$5:$F$300,6)=0)+(Budget!$D$5:$D$300="vierteljährlich")*(MOD(G$5-Budget!$F$5:$F$300,3)=0))*Budget!$C$5:$C$300)) | H7: =SUMPRODUCT((Budget!$A$5:$A$300<>"Einnahmen")*(Budget!$A$5:$A$300<>"")*(((Budget!$D$5:$D$300="monatlich")+(Budget!$D$5:$D$300="wöchentlich")*52/12)*Budget!$C$5:$C$300+((Budget!$D$5:$D$300="jährlich")*(Budget!$F$5:$F$300=H$5)+(Budget!$D$5:$D$300="halbjährlich")*(MOD(H$5-Budget!$F$5:$F$300,6)=0)+(Budget!$D$5:$D$300="vierteljährlich")*(MOD(H$5-Budget!$F$5:$F$300,3)=0))*Budget!$C$5:$C$300)) | I7: =SUMPRODUCT((Budget!$A$5:$A$300<>"Einnahmen")*(Budget!$A$5:$A$300<>"")*(((Budget!$D$5:$D$300="monatlich")+(Budget!$D$5:$D$300="wöchentlich")*52/12)*Budget!$C$5:$C$300+((Budget!$D$5:$D$300="jährlich")*(Budget!$F$5:$F$300=I$5)+(Budget!$D$5:$D$300="halbjährlich")*(MOD(I$5-Budget!$F$5:$F$300,6)=0)+(Budget!$D$5:$D$300="vierteljährlich")*(MOD(I$5-Budget!$F$5:$F$300,3)=0))*Budget!$C$5:$C$300)) | ... M7: =SUMPRODUCT((Budget!$A$5:$A$300<>"Einnahmen")*(Budget!$A$5:$A$300<>"")*(((Budget!$D$5:$D$300="monatlich")+(Budget!$D$5:$D$300="wöchentlich")*52/12)*Budget!$C$5:$C$300+((Budget!$D$5:$D$300="jährlich")*(Budget!$F$5:$F$300=M$5)+(Budget!$D$5:$D$300="halbjährlich")*(MOD(M$5-Budget!$F$5:$F$300,6)=0)+(Budget!$D$5:$D$300="vierteljährlich")*(MOD(M$5-Budget!$F$5:$F$300,3)=0))*Budget!$C$5:$C$300)) | N7: =SUM(B7:M7)
A8: davon periodische Rechnungen | B8: =SUMPRODUCT((Budget!$A$5:$A$300<>"Einnahmen")*(Budget!$A$5:$A$300<>"")*((Budget!$D$5:$D$300="jährlich")*(Budget!$F$5:$F$300=B$5)+(Budget!$D$5:$D$300="halbjährlich")*(MOD(B$5-Budget!$F$5:$F$300,6)=0)+(Budget!$D$5:$D$300="vierteljährlich")*(MOD(B$5-Budget!$F$5:$F$300,3)=0))*Budget!$C$5:$C$300) | C8: =SUMPRODUCT((Budget!$A$5:$A$300<>"Einnahmen")*(Budget!$A$5:$A$300<>"")*((Budget!$D$5:$D$300="jährlich")*(Budget!$F$5:$F$300=C$5)+(Budget!$D$5:$D$300="halbjährlich")*(MOD(C$5-Budget!$F$5:$F$300,6)=0)+(Budget!$D$5:$D$300="vierteljährlich")*(MOD(C$5-Budget!$F$5:$F$300,3)=0))*Budget!$C$5:$C$300) | D8: =SUMPRODUCT((Budget!$A$5:$A$300<>"Einnahmen")*(Budget!$A$5:$A$300<>"")*((Budget!$D$5:$D$300="jährlich")*(Budget!$F$5:$F$300=D$5)+(Budget!$D$5:$D$300="halbjährlich")*(MOD(D$5-Budget!$F$5:$F$300,6)=0)+(Budget!$D$5:$D$300="vierteljährlich")*(MOD(D$5-Budget!$F$5:$F$300,3)=0))*Budget!$C$5:$C$300) | E8: =SUMPRODUCT((Budget!$A$5:$A$300<>"Einnahmen")*(Budget!$A$5:$A$300<>"")*((Budget!$D$5:$D$300="jährlich")*(Budget!$F$5:$F$300=E$5)+(Budget!$D$5:$D$300="halbjährlich")*(MOD(E$5-Budget!$F$5:$F$300,6)=0)+(Budget!$D$5:$D$300="vierteljährlich")*(MOD(E$5-Budget!$F$5:$F$300,3)=0))*Budget!$C$5:$C$300) | F8: =SUMPRODUCT((Budget!$A$5:$A$300<>"Einnahmen")*(Budget!$A$5:$A$300<>"")*((Budget!$D$5:$D$300="jährlich")*(Budget!$F$5:$F$300=F$5)+(Budget!$D$5:$D$300="halbjährlich")*(MOD(F$5-Budget!$F$5:$F$300,6)=0)+(Budget!$D$5:$D$300="vierteljährlich")*(MOD(F$5-Budget!$F$5:$F$300,3)=0))*Budget!$C$5:$C$300) | G8: =SUMPRODUCT((Budget!$A$5:$A$300<>"Einnahmen")*(Budget!$A$5:$A$300<>"")*((Budget!$D$5:$D$300="jährlich")*(Budget!$F$5:$F$300=G$5)+(Budget!$D$5:$D$300="halbjährlich")*(MOD(G$5-Budget!$F$5:$F$300,6)=0)+(Budget!$D$5:$D$300="vierteljährlich")*(MOD(G$5-Budget!$F$5:$F$300,3)=0))*Budget!$C$5:$C$300) | H8: =SUMPRODUCT((Budget!$A$5:$A$300<>"Einnahmen")*(Budget!$A$5:$A$300<>"")*((Budget!$D$5:$D$300="jährlich")*(Budget!$F$5:$F$300=H$5)+(Budget!$D$5:$D$300="halbjährlich")*(MOD(H$5-Budget!$F$5:$F$300,6)=0)+(Budget!$D$5:$D$300="vierteljährlich")*(MOD(H$5-Budget!$F$5:$F$300,3)=0))*Budget!$C$5:$C$300) | I8: =SUMPRODUCT((Budget!$A$5:$A$300<>"Einnahmen")*(Budget!$A$5:$A$300<>"")*((Budget!$D$5:$D$300="jährlich")*(Budget!$F$5:$F$300=I$5)+(Budget!$D$5:$D$300="halbjährlich")*(MOD(I$5-Budget!$F$5:$F$300,6)=0)+(Budget!$D$5:$D$300="vierteljährlich")*(MOD(I$5-Budget!$F$5:$F$300,3)=0))*Budget!$C$5:$C$300) | ... M8: =SUMPRODUCT((Budget!$A$5:$A$300<>"Einnahmen")*(Budget!$A$5:$A$300<>"")*((Budget!$D$5:$D$300="jährlich")*(Budget!$F$5:$F$300=M$5)+(Budget!$D$5:$D$300="halbjährlich")*(MOD(M$5-Budget!$F$5:$F$300,6)=0)+(Budget!$D$5:$D$300="vierteljährlich")*(MOD(M$5-Budget!$F$5:$F$300,3)=0))*Budget!$C$5:$C$300) | N8: =SUM(B8:M8)
A9: Saldo des Monats | B9: =B6-B7 | C9: =C6-C7 | D9: =D6-D7 | E9: =E6-E7 | F9: =F6-F7 | G9: =G6-G7 | H9: =H6-H7 | I9: =I6-I7 | ... M9: =M6-M7 | N9: =SUM(B9:M9)
A10: Kumuliert seit Januar | B10: =B9 | C10: =B10+C9 | D10: =C10+D9 | E10: =D10+E9 | F10: =E10+F9 | G10: =F10+G9 | H10: =G10+H9 | I10: =H10+I9 | J10: =I10+J9 | ... M10: =L10+M9 | N10: =M10
A12: Rot = in diesem Monat geht mehr weg als reinkommt. Mit den monatlichen Rückstellungen (Blatt «Übersicht») wird das ausgeglichen.

Sheet Ist-Vergleich
A1: Ist-Vergleich Essen
A2: Budget kommt aus dem Blatt «Budget» (Spalte «Ist-Kategorie»). Ist-Werte eintragen oder aus der Haushaltskasse übernehmen.
A4: Monat | B4: Budget Lebensmittel | C4: Ist Lebensmittel | D4: Differenz | E4: Budget Auswärts | F4: Ist Auswärts | G4: Differenz
A5: Januar 2026 | B5: =SUMIFS(Budget!$G$5:$G$300,Budget!$K$5:$K$300,"Lebensmittel") | D5: =IF(C5="","",B5-C5) | E5: =SUMIFS(Budget!$G$5:$G$300,Budget!$K$5:$K$300,"Auswärts") | G5: =IF(F5="","",E5-F5)
A6: Februar 2026 | B6: =SUMIFS(Budget!$G$5:$G$300,Budget!$K$5:$K$300,"Lebensmittel") | D6: =IF(C6="","",B6-C6) | E6: =SUMIFS(Budget!$G$5:$G$300,Budget!$K$5:$K$300,"Auswärts") | G6: =IF(F6="","",E6-F6)
A7: März 2026 | B7: =SUMIFS(Budget!$G$5:$G$300,Budget!$K$5:$K$300,"Lebensmittel") | D7: =IF(C7="","",B7-C7) | E7: =SUMIFS(Budget!$G$5:$G$300,Budget!$K$5:$K$300,"Auswärts") | G7: =IF(F7="","",E7-F7)
A8: April 2026 | B8: =SUMIFS(Budget!$G$5:$G$300,Budget!$K$5:$K$300,"Lebensmittel") | D8: =IF(C8="","",B8-C8) | E8: =SUMIFS(Budget!$G$5:$G$300,Budget!$K$5:$K$300,"Auswärts") | G8: =IF(F8="","",E8-F8)
A9: Mai 2026 | B9: =SUMIFS(Budget!$G$5:$G$300,Budget!$K$5:$K$300,"Lebensmittel") | D9: =IF(C9="","",B9-C9) | E9: =SUMIFS(Budget!$G$5:$G$300,Budget!$K$5:$K$300,"Auswärts") | G9: =IF(F9="","",E9-F9)
A10: Juni 2026 | B10: =SUMIFS(Budget!$G$5:$G$300,Budget!$K$5:$K$300,"Lebensmittel") | D10: =IF(C10="","",B10-C10) | E10: =SUMIFS(Budget!$G$5:$G$300,Budget!$K$5:$K$300,"Auswärts") | G10: =IF(F10="","",E10-F10)
A11: Juli 2026 | B11: =SUMIFS(Budget!$G$5:$G$300,Budget!$K$5:$K$300,"Lebensmittel") | D11: =IF(C11="","",B11-C11) | E11: =SUMIFS(Budget!$G$5:$G$300,Budget!$K$5:$K$300,"Auswärts") | G11: =IF(F11="","",E11-F11)
A12: August 2026 | B12: =SUMIFS(Budget!$G$5:$G$300,Budget!$K$5:$K$300,"Lebensmittel") | D12: =IF(C12="","",B12-C12) | E12: =SUMIFS(Budget!$G$5:$G$300,Budget!$K$5:$K$300,"Auswärts") | G12: =IF(F12="","",E12-F12)
A13: September 2026 | B13: =SUMIFS(Budget!$G$5:$G$300,Budget!$K$5:$K$300,"Lebensmittel") | D13: =IF(C13="","",B13-C13) | E13: =SUMIFS(Budget!$G$5:$G$300,Budget!$K$5:$K$300,"Auswärts") | G13: =IF(F13="","",E13-F13)
A14: Oktober 2026 | B14: =SUMIFS(Budget!$G$5:$G$300,Budget!$K$5:$K$300,"Lebensmittel") | D14: =IF(C14="","",B14-C14) | E14: =SUMIFS(Budget!$G$5:$G$300,Budget!$K$5:$K$300,"Auswärts") | G14: =IF(F14="","",E14-F14)
A15: November 2026 | B15: =SUMIFS(Budget!$G$5:$G$300,Budget!$K$5:$K$300,"Lebensmittel") | D15: =IF(C15="","",B15-C15) | E15: =SUMIFS(Budget!$G$5:$G$300,Budget!$K$5:$K$300,"Auswärts") | G15: =IF(F15="","",E15-F15)
A16: Dezember 2026 | B16: =SUMIFS(Budget!$G$5:$G$300,Budget!$K$5:$K$300,"Lebensmittel") | D16: =IF(C16="","",B16-C16) | E16: =SUMIFS(Budget!$G$5:$G$300,Budget!$K$5:$K$300,"Auswärts") | G16: =IF(F16="","",E16-F16)
A17: Total | B17: =SUMPRODUCT((C5:C16<>"")*B5:B16) | C17: =SUM(C5:C16) | D17: =SUM(D5:D16) | E17: =SUMPRODUCT((F5:F16<>"")*E5:E16) | F17: =SUM(F5:F16) | G17: =SUM(G5:G16) | I17: Budget-Total zählt nur Monate mit Ist-Wert. Differenz positiv = unter Budget.

Sheet Anleitung
B1: So funktioniert die Budget-Tabelle
B2: Erstellt mit «Kasse unterwegs» am 13.10.2026
B4: 1. Blatt «Budget» | C4: Pro Posten Betrag, «Wie oft», «Wer» und bei jährlichen Rechnungen den Fälligkeitsmonat eintragen. Jahresbeträge (Steuern, Versicherungen) einfach als Jahresbetrag – umgerechnet wird automatisch.
B5: 2. Blatt «Übersicht» | C5: Zeigt Einnahmen, Ausgaben je Bereich, Sparen, was übrig bleibt, wer wie viel trägt und wie viel jede Person aufs gemeinsame Konto überweist.
B6: 3. Blatt «Jahresplan» | C6: Zeigt Monat für Monat, wann grosse Rechnungen fällig sind und ob das Geld reicht.
B7: 4. Blatt «Ist-Vergleich» | C7: Ist-Ausgaben für Lebensmittel und Auswärts essen pro Monat – aus der Haushaltskasse oder von Hand.
B8: Fälligkeit | C8: Bei jährlichen, halbjährlichen und vierteljährlichen Posten den Monat (1–12) der ersten Rechnung eintragen – sonst fehlt die Rechnung im Jahresplan.
B9: Neue Posten | C9: Innerhalb einer Gruppe eine Zeile einfügen und in Spalte A den Gruppennamen stehen lassen. Die Formeln decken die Zeilen 5 bis 300 ab.
B11: Legende
B12: Eingabe | C12: Blaue Schrift auf Gelb: hier eintragen oder ändern.
B13: =1234.5 | C13: Schwarze Schrift: Formel, rechnet selbst – nicht überschreiben.
B15: Beispielzeile (so wird ein Posten ausgefüllt)
B16: Posten | C16: Betrag CHF | D16: Wie oft | E16: Wer | F16: Fällig | G16: Ergibt pro Monat
B17: Steuern (Beispiel) | C17: 6000 | D17: jährlich | E17: gemeinsam | F17: 3 | G17: =C17/12
B19: Wie oft | C19: Faktor pro Monat
B20: monatlich | C20: =Listen!B2
B21: wöchentlich | C21: =Listen!B3
B22: vierteljährlich | C22: =Listen!B4
B23: halbjährlich | C23: =Listen!B5
B24: jährlich | C24: =Listen!B6
B26: Hinweis | C26: Die Faustregeln in der Übersicht sind allgemeine Richtwerte. Für eine persönliche Budgetberatung: Budgetberatung Schweiz (budgetberatung.ch).

Sheet Listen
A1: Wie oft | B1: Faktor pro Monat
A2: monatlich | B2: =1
A3: wöchentlich | B3: =52/12
A4: vierteljährlich | B4: =1/3
A5: halbjährlich | B5: =1/6
A6: jährlich | B6: =1/12
